{
    "Products": [
        {
            "imageTsrc": "https://cdn.eyemyeye.com/shared/images/products/S12A2001/S12A2001-1.jpg",
            "productRefLink": "smoketintedwayfarersunglasses",
            "rating": "4.2",
            "colors": "Black,BrownSmoke",
            "price": "925",
            "mPrice": "2199",
            "name": "ALF",
            "shape": "Wayfarer",
            "gender": "Men,Women",
            "style": "Tinted",
            "dimension": "50-19-150",
            "productType": "sunglasses",
            "productId": "S66B4733",
            "userRated": "3",
            "quntity": "0",
            "id": 995042187
        },
        {
            "imageTsrc": "https://cdn.eyemyeye.com/shared/images/products/S15C4698/S15C4698-1.jpg",
            "productRefLink": "smoketintedwayfarersunglasses",
            "rating": "3.5",
            "colors": "Smoke",
            "price": "925",
            "mPrice": "2199",
            "name": "ALF",
            "shape": "Wayfarer",
            "gender": "Men,Women",
            "style": "Tinted",
            "dimension": "50-18-138",
            "productType": "sunglasses",
            "productId": "S66A4777",
            "userRated": "3",
            "quntity": "0",
            "id": 501892623
        },
        {
            "imageTsrc": "https://cdn.eyemyeye.com/shared/images/products/S25B3668/S25B3668-1.jpg",
            "productRefLink": "greentintedcateyesunglasses",
            "rating": "4.5",
            "colors": "Blue,Green",
            "price": "925",
            "mPrice": "2199",
            "name": "SOIGNEE",
            "shape": "Cateye",
            "gender": "Women",
            "style": "Tinted",
            "dimension": "49-18-135",
            "productType": "sunglasses",
            "productId": "S35A3289",
            "userRated": "18",
            "quntity": "0",
            "id": 593327273
        },
        {
            "imageTsrc": "https://cdn.eyemyeye.com/shared/images/products/S75B2001/S75B2001-1.jpg",
            "productRefLink": "browntintedwayfarersunglasses",
            "rating": "2.8",
            "colors": "Black,Smoke,Brown",
            "price": "925",
            "mPrice": "2199",
            "name": "ALF",
            "shape": "Wayfarer",
            "gender": "Men,Women",
            "style": "Tinted",
            "dimension": "50-19-150",
            "productType": "sunglasses",
            "productId": "S15C4733",
            "userRated": "58",
            "quntity": "0",
            "id": 354915058
        },
        {
            "imageTsrc": "https://cdn.eyemyeye.com/shared/images/products/S12A4733/S12A4733-1.jpg",
            "productRefLink": "browntintedroundsunglasses",
            "rating": "4.2",
            "colors": "Brown",
            "price": "925",
            "mPrice": "2199",
            "name": "ELISIAN",
            "shape": "Round",
            "gender": "Men,Women",
            "style": "Tinted",
            "dimension": "48-28-138",
            "productType": "sunglasses",
            "productId": "S15C3994",
            "userRated": "5",
            "quntity": "0",
            "id": 693813978
        },
        {
            "imageTsrc": "https://cdn.eyemyeye.com/shared/images/products/S66A4672/S66A4672-1.jpg",
            "productRefLink": "browntintedwayfarersunglasses",
            "rating": "3.5",
            "colors": "Smoke,Blue,Brown",
            "price": "925",
            "mPrice": "2199",
            "name": "ELISIAN",
            "shape": "Wayfarer",
            "gender": "Men,Women",
            "style": "Tinted",
            "dimension": "52-18-140",
            "productType": "sunglasses",
            "productId": "S15B3934",
            "userRated": "21",
            "quntity": "0",
            "id": 575968083
        },
        {
            "imageTsrc": "https://cdn.eyemyeye.com/shared/images/products/S25B3676/S25B3676-1.jpg",
            "productRefLink": "nvgbyessilorsilvermirrorwraparoundsunglasses",
            "rating": "2.5",
            "colors": "Silver",
            "price": "1799",
            "mPrice": "2199",
            "name": "2.5NVG",
            "shape": "Wrapround",
            "gender": "Men,Women",
            "style": "Mirror",
            "dimension": "64-15-132",
            "productType": "sunglasses",
            "productId": "S10C1510",
            "userRated": "45",
            "quntity": "0",
            "id": 605629053
        },
        {
            "imageTsrc": "https://cdn.eyemyeye.com/shared/images/products/S66B2000/S66B2000-1.jpg",
            "productRefLink": "greentintedwraparoundsunglasses",
            "rating": "3.5",
            "colors": "Brown,Green,Green",
            "price": "925",
            "mPrice": "2199",
            "name": "ALF",
            "shape": "Wrapround",
            "gender": "Men",
            "style": "Tinted",
            "dimension": "53-15-149",
            "productType": "sunglasses",
            "productId": "S35B4713",
            "userRated": "3",
            "quntity": "0",
            "id": 403377823
        },
        {
            "imageTsrc": "https://cdn.eyemyeye.com/shared/images/products/S15B4211/S15B4211-1.jpg",
            "productRefLink": "bluetintedwayfarersunglasses",
            "rating": "3.5",
            "colors": "Blue",
            "price": "925",
            "mPrice": "2199",
            "name": "ALF",
            "shape": "Wayfarer",
            "gender": "Men,Women",
            "style": "Tinted",
            "dimension": "51-18-145",
            "productType": "sunglasses",
            "productId": "S20A4828",
            "userRated": "9",
            "quntity": "0",
            "id": 815280696
        },
        {
            "imageTsrc": "https://cdn.eyemyeye.com/shared/images/products/S25B3667/S25B3667-1.jpg",
            "productRefLink": "purpletintedwayfarersunglases",
            "rating": "3.5",
            "colors": "Purple",
            "price": "925",
            "mPrice": "2199",
            "name": "ELISIAN",
            "shape": "Wayfarer",
            "gender": "Women",
            "style": "Tinted",
            "dimension": "55-17-146",
            "productType": "sunglasses",
            "productId": "S17B4175",
            "userRated": "",
            "quntity": "0",
            "id": 747700933
        },
        {
            "imageTsrc": "https://cdn.eyemyeye.com/shared/images/products/S66B4680/S66B4680-1.jpg",
            "productRefLink": "purpletintedwayfarersunglasses",
            "rating": "2.4",
            "colors": "Purple",
            "price": "925",
            "mPrice": "2199",
            "name": "ALF",
            "shape": "Wayfarer",
            "gender": "Men",
            "style": "Tinted",
            "dimension": "50-14-140",
            "productType": "sunglasses",
            "productId": "S17A3915",
            "userRated": "15",
            "quntity": "0",
            "id": 704992754
        },
        {
            "imageTsrc": "https://cdn.eyemyeye.com/shared/images/products/S17A3298/S17A3298-1.jpg",
            "productRefLink": "browntintedwayfarersunglasses",
            "rating": "3.5",
            "colors": "Smoke,Brown",
            "price": "925",
            "mPrice": "2199",
            "name": "ELISIAN",
            "shape": "Wayfarer",
            "gender": "Men",
            "style": "Tinted",
            "dimension": "53-19-141",
            "productType": "sunglasses",
            "productId": "S15A3540",
            "userRated": "56",
            "quntity": "0",
            "id": 609473537
        },
        {
            "imageTsrc": "https://cdn.eyemyeye.com/shared/images/products/S25B3675/S25B3675-1.jpg",
            "productRefLink": "blacktintedwayfarersunglasses",
            "rating": "3.5",
            "colors": "Smoke,Black",
            "price": "925",
            "mPrice": "2199",
            "name": "ALF",
            "shape": "Wayfarer",
            "gender": "Men,Women",
            "style": "Tinted",
            "dimension": "53-18-140",
            "productType": "sunglasses",
            "productId": "S12C4706",
            "userRated": "7",
            "quntity": "0",
            "id": 747933577
        },
        {
            "imageTsrc": "https://cdn.eyemyeye.com/shared/images/products/S66B4667/S66B4667-1.jpg",
            "productRefLink": "multicolortintedbutterflysunglasses",
            "rating": "3.5",
            "colors": "Multicolor",
            "price": "925",
            "mPrice": "2199",
            "name": "ALF",
            "shape": "Butterfly",
            "gender": "Women",
            "style": "Tinted",
            "dimension": "52-18-140",
            "productType": "sunglasses",
            "productId": "S67A4758",
            "userRated": "",
            "quntity": "0",
            "id": 532449205
        },
        {
            "imageTsrc": "https://cdn.eyemyeye.com/shared/images/products/S10B4340/S10B4340-1.jpg",
            "productRefLink": "smoketintedwraparoundsunglasses",
            "rating": "3.5",
            "colors": "Blue,Black,Smoke",
            "price": "925",
            "mPrice": "2199",
            "name": "ALF",
            "shape": "Wrapround",
            "gender": "Men",
            "style": "Tinted",
            "dimension": "53-15-149",
            "productType": "sunglasses",
            "productId": "S66C4712",
            "userRated": "6",
            "quntity": "0",
            "id": 219143397
        }
    ]
}